{"cameraMode":{"drawMode":0,"name":"Shaded","section":"Shading Mode"},"sceneLighting":true,"audioPlay":false,"sceneViewState":{"m_AlwaysRefresh":false,"showFog":true,"showSkybox":true,"showFlares":true,"showImageEffects":true,"showParticleSystems":true,"showVisualEffectGraphs":true,"m_FxEnabled":true},"in2DMode":false,"pivot":{"x":-0.13075384497642518,"y":1.9656190872192383,"z":4.699828624725342},"rotation":{"x":0.013167987577617169,"y":0.9598472118377686,"z":-0.2767947018146515,"w":0.04339738190174103},"size":1.2828117609024048,"orthographic":false}